{
	"info": {
		"_postman_id": "b3c5c54d-258f-4aa8-a601-8c2ee11b43df",
		"name": "Blog Backend",
		"schema": "https://schema.getpostman.com/json/collection/v2.1.0/collection.json"
	},
	"item": [
		{
			"name": "Usuários",
			"item": [
				{
					"name": "List Users",
					"protocolProfileBehavior": {
						"disableBodyPruning": true
					},
					"request": {
						"auth": {
							"type": "bearer",
							"bearer": [
								{
									"key": "token",
									"value": "eyJhbGciOiJIUzI1NiIsInR5cCI6IkpXVCJ9.eyJzdWIiOiJtZXUyQGVtYWlsLmNvbSIsImlzcyI6ImJsb2ctYmFja2VuZCIsImlhdCI6MTYyODY1MzE0MX0.Q-gXZMhPvzChxtNkS2JbFbv-pA6CyMsThHUcFyjBBPg",
									"type": "string"
								}
							]
						},
						"method": "GET",
						"header": [],
						"body": {
							"mode": "raw",
							"raw": "",
							"options": {
								"raw": {
									"language": "json"
								}
							}
						},
						"url": {
							"raw": "http://localhost:3000/user",
							"protocol": "http",
							"host": [
								"localhost"
							],
							"port": "3000",
							"path": [
								"user"
							]
						}
					},
					"response": []
				},
				{
					"name": "Find User By Id",
					"protocolProfileBehavior": {
						"disableBodyPruning": true
					},
					"request": {
						"auth": {
							"type": "bearer",
							"bearer": [
								{
									"key": "token",
									"value": "eyJhbGciOiJIUzI1NiIsInR5cCI6IkpXVCJ9.eyJzdWIiOiJtZXUyQGVtYWlsLmNvbSIsImlzcyI6ImJsb2ctYmFja2VuZCIsImlhdCI6MTYyODY1MzE0MX0.Q-gXZMhPvzChxtNkS2JbFbv-pA6CyMsThHUcFyjBBPg",
									"type": "string"
								}
							]
						},
						"method": "GET",
						"header": [],
						"body": {
							"mode": "raw",
							"raw": "",
							"options": {
								"raw": {
									"language": "json"
								}
							}
						},
						"url": {
							"raw": "http://localhost:3000/user/444",
							"protocol": "http",
							"host": [
								"localhost"
							],
							"port": "3000",
							"path": [
								"user",
								"444"
							]
						}
					},
					"response": []
				},
				{
					"name": "Deletar My User",
					"request": {
						"auth": {
							"type": "bearer",
							"bearer": [
								{
									"key": "token",
									"value": "eyJhbGciOiJIUzI1NiIsInR5cCI6IkpXVCJ9.eyJzdWIiOiJtZXUyQGVtYWlsLmNvbSIsImlzcyI6ImJsb2ctYmFja2VuZCIsImlhdCI6MTYyODY1MzE0MX0.Q-gXZMhPvzChxtNkS2JbFbv-pA6CyMsThHUcFyjBBPg",
									"type": "string"
								}
							]
						},
						"method": "DELETE",
						"header": [],
						"body": {
							"mode": "raw",
							"raw": "",
							"options": {
								"raw": {
									"language": "json"
								}
							}
						},
						"url": {
							"raw": "http://localhost:3000/user/me",
							"protocol": "http",
							"host": [
								"localhost"
							],
							"port": "3000",
							"path": [
								"user",
								"me"
							]
						}
					},
					"response": []
				},
				{
					"name": "Create User",
					"request": {
						"method": "POST",
						"header": [],
						"body": {
							"mode": "raw",
							"raw": "{\n\"id\": \"401465483996\",\n\"displayName\": \"Brett\",\n\"email\": \"brett@email.com\",\n\"password\": \"123456\",\n\"image\": \"http://4.bp.blogspot.com/_YA50adQ-7vQ/S1gfR_6ufpI/AAAAAAAAAAk/1ErJGgRWZDg/S45/brett.png\"\n}",
							"options": {
								"raw": {
									"language": "json"
								}
							}
						},
						"url": {
							"raw": "http://localhost:3000/user",
							"protocol": "http",
							"host": [
								"localhost"
							],
							"port": "3000",
							"path": [
								"user"
							]
						}
					},
					"response": []
				}
			]
		},
		{
			"name": "Posts",
			"item": [
				{
					"name": "Create Post",
					"request": {
						"method": "POST",
						"header": [],
						"body": {
							"mode": "raw",
							"raw": "{\n    \"title\":\"NADA\",\n    \"content\": \"titulo\"\n}",
							"options": {
								"raw": {
									"language": "json"
								}
							}
						},
						"url": {
							"raw": "http://localhost:3000/post",
							"protocol": "http",
							"host": [
								"localhost"
							],
							"port": "3000",
							"path": [
								"post"
							]
						}
					},
					"response": []
				},
				{
					"name": "List Posts",
					"protocolProfileBehavior": {
						"disableBodyPruning": true
					},
					"request": {
						"method": "GET",
						"header": [],
						"body": {
							"mode": "raw",
							"raw": "",
							"options": {
								"raw": {
									"language": "json"
								}
							}
						},
						"url": {
							"raw": "http://localhost:3000/post",
							"protocol": "http",
							"host": [
								"localhost"
							],
							"port": "3000",
							"path": [
								"post"
							]
						}
					},
					"response": []
				},
				{
					"name": "Search Post",
					"protocolProfileBehavior": {
						"disableBodyPruning": true
					},
					"request": {
						"method": "GET",
						"header": [],
						"body": {
							"mode": "raw",
							"raw": "",
							"options": {
								"raw": {
									"language": "json"
								}
							}
						},
						"url": {
							"raw": "http://localhost:3000/post/search",
							"protocol": "http",
							"host": [
								"localhost"
							],
							"port": "3000",
							"path": [
								"post",
								"search"
							]
						}
					},
					"response": []
				},
				{
					"name": "Find Post By id",
					"protocolProfileBehavior": {
						"disableBodyPruning": true
					},
					"request": {
						"method": "GET",
						"header": [],
						"body": {
							"mode": "raw",
							"raw": "",
							"options": {
								"raw": {
									"language": "json"
								}
							}
						},
						"url": {
							"raw": "http://localhost:3000/post",
							"protocol": "http",
							"host": [
								"localhost"
							],
							"port": "3000",
							"path": [
								"post"
							]
						}
					},
					"response": []
				},
				{
					"name": "Delete Post By id",
					"protocolProfileBehavior": {
						"disableBodyPruning": true
					},
					"request": {
						"method": "GET",
						"header": [],
						"body": {
							"mode": "raw",
							"raw": "",
							"options": {
								"raw": {
									"language": "json"
								}
							}
						},
						"url": {
							"raw": "http://localhost:3000/post",
							"protocol": "http",
							"host": [
								"localhost"
							],
							"port": "3000",
							"path": [
								"post"
							]
						}
					},
					"response": []
				},
				{
					"name": "Update Post By id Copy",
					"request": {
						"method": "PUT",
						"header": [],
						"body": {
							"mode": "raw",
							"raw": "{\n    \"title\":\"TESTE\",\n    \"content\":\"content2\"\n}",
							"options": {
								"raw": {
									"language": "json"
								}
							}
						},
						"url": {
							"raw": "http://localhost:3000/post/1",
							"protocol": "http",
							"host": [
								"localhost"
							],
							"port": "3000",
							"path": [
								"post",
								"1"
							]
						}
					},
					"response": []
				}
			],
			"auth": {
				"type": "bearer",
				"bearer": [
					{
						"key": "token",
						"value": "eyJhbGciOiJIUzI1NiIsInR5cCI6IkpXVCJ9.eyJzdWIiOnsiZW1haWwiOiJtZXV3MjcyMjJAZW1haWwuY29tIiwiaWQiOjV9LCJpc3MiOiJibG9nLWJhY2tlbmQiLCJpYXQiOjE2Mjg2NjEyMTZ9.8pZ1kBm3K_w-kJMzqBv7E4nBiv6DchvstrRkgc8pwX4",
						"type": "string"
					}
				]
			},
			"event": [
				{
					"listen": "prerequest",
					"script": {
						"type": "text/javascript",
						"exec": [
							""
						]
					}
				},
				{
					"listen": "test",
					"script": {
						"type": "text/javascript",
						"exec": [
							""
						]
					}
				}
			]
		},
		{
			"name": "Health Check",
			"request": {
				"method": "GET",
				"header": [],
				"url": null,
				"description": "A Rota Health Check serve apenas para verificar se a aplicação está de pé no servidor.\n\nNão necessita de autenticação"
			},
			"response": []
		},
		{
			"name": "Login",
			"request": {
				"method": "POST",
				"header": [],
				"body": {
					"mode": "raw",
					"raw": "{\n\"email\": \"meuw2222@email.com\",\n    \"password\":\"123456\"\n}",
					"options": {
						"raw": {
							"language": "json"
						}
					}
				},
				"url": {
					"raw": "http://localhost:3000/login",
					"protocol": "http",
					"host": [
						"localhost"
					],
					"port": "3000",
					"path": [
						"login"
					]
				}
			},
			"response": []
		}
	]
}